{
  "_meta": {
    "version": "2.0",
    "notes": "Общий реестр карт всех колод. Matching имени карты при записи расклада идёт по en/ru/aliases (case-insensitive). Card id в интерпретациях — всегда EN. UI показывает RU + EN мелким шрифтом."
  },
  "rider-waite": {
    "name_en": "Rider-Waite Tarot",
    "name_ru": "Таро Уэйта",
    "folder": "rider-waite",
    "status": "complete",
    "cards": [
      {"file": "00_fool.jpg", "en": "The Fool", "ru": "Шут", "aliases": ["дурак", "глупец"]},
      {"file": "01_magician.jpg", "en": "The Magician", "ru": "Маг", "aliases": ["волшебник"]},
      {"file": "02_high_priestess.jpg", "en": "The High Priestess", "ru": "Жрица", "aliases": ["верховная жрица", "priestess"]},
      {"file": "03_empress.jpg", "en": "The Empress", "ru": "Императрица", "aliases": []},
      {"file": "04_emperor.jpg", "en": "The Emperor", "ru": "Император", "aliases": []},
      {"file": "05_hierophant.jpg", "en": "The Hierophant", "ru": "Иерофант", "aliases": ["жрец", "папа"]},
      {"file": "06_lovers.jpg", "en": "The Lovers", "ru": "Влюблённые", "aliases": ["влюбленные", "любовники"]},
      {"file": "07_chariot.jpg", "en": "The Chariot", "ru": "Колесница", "aliases": []},
      {"file": "08_strength.jpg", "en": "Strength", "ru": "Сила", "aliases": []},
      {"file": "09_hermit.jpg", "en": "The Hermit", "ru": "Отшельник", "aliases": []},
      {"file": "10_wheel_of_fortune.jpg", "en": "Wheel of Fortune", "ru": "Колесо Фортуны", "aliases": ["фортуна", "колесо"]},
      {"file": "11_justice.jpg", "en": "Justice", "ru": "Справедливость", "aliases": ["правосудие"]},
      {"file": "12_hanged_man.jpg", "en": "The Hanged Man", "ru": "Повешенный", "aliases": []},
      {"file": "13_death.jpg", "en": "Death", "ru": "Смерть", "aliases": []},
      {"file": "14_temperance.jpg", "en": "Temperance", "ru": "Умеренность", "aliases": []},
      {"file": "15_devil.jpg", "en": "The Devil", "ru": "Дьявол", "aliases": []},
      {"file": "16_tower.jpg", "en": "The Tower", "ru": "Башня", "aliases": []},
      {"file": "17_star.jpg", "en": "The Star", "ru": "Звезда", "aliases": []},
      {"file": "18_moon.jpg", "en": "The Moon", "ru": "Луна", "aliases": []},
      {"file": "19_sun.jpg", "en": "The Sun", "ru": "Солнце", "aliases": []},
      {"file": "20_judgement.jpg", "en": "Judgement", "ru": "Суд", "aliases": ["суд страшный", "judgment"]},
      {"file": "21_world.jpg", "en": "The World", "ru": "Мир", "aliases": ["вселенная"]},
      {"file": "wa_01_ace.jpg", "en": "Ace of Wands", "ru": "Туз Жезлов", "aliases": ["туз посохов"]},
      {"file": "wa_02.jpg", "en": "Two of Wands", "ru": "Двойка Жезлов", "aliases": ["2 жезлов"]},
      {"file": "wa_03.jpg", "en": "Three of Wands", "ru": "Тройка Жезлов", "aliases": ["3 жезлов"]},
      {"file": "wa_04.jpg", "en": "Four of Wands", "ru": "Четвёрка Жезлов", "aliases": ["4 жезлов", "четверка жезлов"]},
      {"file": "wa_05.jpg", "en": "Five of Wands", "ru": "Пятёрка Жезлов", "aliases": ["5 жезлов", "пятерка жезлов"]},
      {"file": "wa_06.jpg", "en": "Six of Wands", "ru": "Шестёрка Жезлов", "aliases": ["6 жезлов", "шестерка жезлов"]},
      {"file": "wa_07.jpg", "en": "Seven of Wands", "ru": "Семёрка Жезлов", "aliases": ["7 жезлов", "семерка жезлов"]},
      {"file": "wa_08.jpg", "en": "Eight of Wands", "ru": "Восьмёрка Жезлов", "aliases": ["8 жезлов", "восьмерка жезлов"]},
      {"file": "wa_09.jpg", "en": "Nine of Wands", "ru": "Девятка Жезлов", "aliases": ["9 жезлов"]},
      {"file": "wa_10.jpg", "en": "Ten of Wands", "ru": "Десятка Жезлов", "aliases": ["10 жезлов"]},
      {"file": "wa_11_page.jpg", "en": "Page of Wands", "ru": "Паж Жезлов", "aliases": []},
      {"file": "wa_12_knight.jpg", "en": "Knight of Wands", "ru": "Рыцарь Жезлов", "aliases": []},
      {"file": "wa_13_queen.jpg", "en": "Queen of Wands", "ru": "Королева Жезлов", "aliases": []},
      {"file": "wa_14_king.jpg", "en": "King of Wands", "ru": "Король Жезлов", "aliases": []},
      {"file": "cu_01_ace.jpg", "en": "Ace of Cups", "ru": "Туз Кубков", "aliases": []},
      {"file": "cu_02.jpg", "en": "Two of Cups", "ru": "Двойка Кубков", "aliases": ["2 кубков"]},
      {"file": "cu_03.jpg", "en": "Three of Cups", "ru": "Тройка Кубков", "aliases": ["3 кубков"]},
      {"file": "cu_04.jpg", "en": "Four of Cups", "ru": "Четвёрка Кубков", "aliases": ["4 кубков", "четверка кубков"]},
      {"file": "cu_05.jpg", "en": "Five of Cups", "ru": "Пятёрка Кубков", "aliases": ["5 кубков", "пятерка кубков"]},
      {"file": "cu_06.jpg", "en": "Six of Cups", "ru": "Шестёрка Кубков", "aliases": ["6 кубков", "шестерка кубков"]},
      {"file": "cu_07.jpg", "en": "Seven of Cups", "ru": "Семёрка Кубков", "aliases": ["7 кубков", "семерка кубков"]},
      {"file": "cu_08.jpg", "en": "Eight of Cups", "ru": "Восьмёрка Кубков", "aliases": ["8 кубков", "восьмерка кубков"]},
      {"file": "cu_09.jpg", "en": "Nine of Cups", "ru": "Девятка Кубков", "aliases": ["9 кубков"]},
      {"file": "cu_10.jpg", "en": "Ten of Cups", "ru": "Десятка Кубков", "aliases": ["10 кубков"]},
      {"file": "cu_11_page.jpg", "en": "Page of Cups", "ru": "Паж Кубков", "aliases": []},
      {"file": "cu_12_knight.jpg", "en": "Knight of Cups", "ru": "Рыцарь Кубков", "aliases": []},
      {"file": "cu_13_queen.jpg", "en": "Queen of Cups", "ru": "Королева Кубков", "aliases": []},
      {"file": "cu_14_king.jpg", "en": "King of Cups", "ru": "Король Кубков", "aliases": []},
      {"file": "sw_01_ace.jpg", "en": "Ace of Swords", "ru": "Туз Мечей", "aliases": []},
      {"file": "sw_02.jpg", "en": "Two of Swords", "ru": "Двойка Мечей", "aliases": ["2 мечей"]},
      {"file": "sw_03.jpg", "en": "Three of Swords", "ru": "Тройка Мечей", "aliases": ["3 мечей"]},
      {"file": "sw_04.jpg", "en": "Four of Swords", "ru": "Четвёрка Мечей", "aliases": ["4 мечей", "четверка мечей"]},
      {"file": "sw_05.jpg", "en": "Five of Swords", "ru": "Пятёрка Мечей", "aliases": ["5 мечей", "пятерка мечей"]},
      {"file": "sw_06.jpg", "en": "Six of Swords", "ru": "Шестёрка Мечей", "aliases": ["6 мечей", "шестерка мечей"]},
      {"file": "sw_07.jpg", "en": "Seven of Swords", "ru": "Семёрка Мечей", "aliases": ["7 мечей", "семерка мечей"]},
      {"file": "sw_08.jpg", "en": "Eight of Swords", "ru": "Восьмёрка Мечей", "aliases": ["8 мечей", "восьмерка мечей"]},
      {"file": "sw_09.jpg", "en": "Nine of Swords", "ru": "Девятка Мечей", "aliases": ["9 мечей"]},
      {"file": "sw_10.jpg", "en": "Ten of Swords", "ru": "Десятка Мечей", "aliases": ["10 мечей"]},
      {"file": "sw_11_page.jpg", "en": "Page of Swords", "ru": "Паж Мечей", "aliases": []},
      {"file": "sw_12_knight.jpg", "en": "Knight of Swords", "ru": "Рыцарь Мечей", "aliases": []},
      {"file": "sw_13_queen.jpg", "en": "Queen of Swords", "ru": "Королева Мечей", "aliases": []},
      {"file": "sw_14_king.jpg", "en": "King of Swords", "ru": "Король Мечей", "aliases": []},
      {"file": "pe_01_ace.jpg", "en": "Ace of Pentacles", "ru": "Туз Пентаклей", "aliases": ["туз монет", "туз динариев", "ace of coins"]},
      {"file": "pe_02.jpg", "en": "Two of Pentacles", "ru": "Двойка Пентаклей", "aliases": ["2 пентаклей"]},
      {"file": "pe_03.jpg", "en": "Three of Pentacles", "ru": "Тройка Пентаклей", "aliases": ["3 пентаклей"]},
      {"file": "pe_04.jpg", "en": "Four of Pentacles", "ru": "Четвёрка Пентаклей", "aliases": ["4 пентаклей", "четверка пентаклей"]},
      {"file": "pe_05.jpg", "en": "Five of Pentacles", "ru": "Пятёрка Пентаклей", "aliases": ["5 пентаклей", "пятерка пентаклей"]},
      {"file": "pe_06.jpg", "en": "Six of Pentacles", "ru": "Шестёрка Пентаклей", "aliases": ["6 пентаклей", "шестерка пентаклей"]},
      {"file": "pe_07.jpg", "en": "Seven of Pentacles", "ru": "Семёрка Пентаклей", "aliases": ["7 пентаклей", "семерка пентаклей"]},
      {"file": "pe_08.jpg", "en": "Eight of Pentacles", "ru": "Восьмёрка Пентаклей", "aliases": ["8 пентаклей", "восьмерка пентаклей"]},
      {"file": "pe_09.jpg", "en": "Nine of Pentacles", "ru": "Девятка Пентаклей", "aliases": ["9 пентаклей"]},
      {"file": "pe_10.jpg", "en": "Ten of Pentacles", "ru": "Десятка Пентаклей", "aliases": ["10 пентаклей"]},
      {"file": "pe_11_page.jpg", "en": "Page of Pentacles", "ru": "Паж Пентаклей", "aliases": []},
      {"file": "pe_12_knight.jpg", "en": "Knight of Pentacles", "ru": "Рыцарь Пентаклей", "aliases": []},
      {"file": "pe_13_queen.jpg", "en": "Queen of Pentacles", "ru": "Королева Пентаклей", "aliases": []},
      {"file": "pe_14_king.jpg", "en": "King of Pentacles", "ru": "Король Пентаклей", "aliases": []}
    ]
  },
  "dark-wood": {
    "name_en": "Dark Wood Tarot",
    "name_ru": "Тёмный лес",
    "folder": "dark-wood",
    "status": "pending",
    "notes": "Имена файлов и id карт идентичны rider-waite для совместимости. Подгружай по готовым именам.",
    "cards_mirror": "rider-waite"
  },
  "deviant-moon": {
    "name_en": "Deviant Moon Tarot",
    "name_ru": "Луна отшельника",
    "folder": "deviant-moon",
    "status": "pending",
    "notes": "Имена файлов и id карт идентичны rider-waite для совместимости.",
    "cards_mirror": "rider-waite"
  },
  "lenormand": {
    "name_en": "Lenormand Classic",
    "name_ru": "Ленорман классический",
    "folder": "lenormand",
    "status": "pending",
    "cards": [
      {"file": "01_rider.jpg", "en": "Rider", "ru": "Всадник", "aliases": ["naездник"]},
      {"file": "02_clover.jpg", "en": "Clover", "ru": "Клевер", "aliases": []},
      {"file": "03_ship.jpg", "en": "Ship", "ru": "Корабль", "aliases": []},
      {"file": "04_house.jpg", "en": "House", "ru": "Дом", "aliases": []},
      {"file": "05_tree.jpg", "en": "Tree", "ru": "Дерево", "aliases": []},
      {"file": "06_clouds.jpg", "en": "Clouds", "ru": "Облака", "aliases": ["тучи"]},
      {"file": "07_snake.jpg", "en": "Snake", "ru": "Змея", "aliases": []},
      {"file": "08_coffin.jpg", "en": "Coffin", "ru": "Гроб", "aliases": []},
      {"file": "09_bouquet.jpg", "en": "Bouquet", "ru": "Букет", "aliases": ["цветы"]},
      {"file": "10_scythe.jpg", "en": "Scythe", "ru": "Коса", "aliases": []},
      {"file": "11_whip.jpg", "en": "Whip", "ru": "Метла", "aliases": ["розги", "кнут"]},
      {"file": "12_birds.jpg", "en": "Birds", "ru": "Птицы", "aliases": ["совы"]},
      {"file": "13_child.jpg", "en": "Child", "ru": "Ребёнок", "aliases": ["ребенок", "дитя"]},
      {"file": "14_fox.jpg", "en": "Fox", "ru": "Лиса", "aliases": []},
      {"file": "15_bear.jpg", "en": "Bear", "ru": "Медведь", "aliases": []},
      {"file": "16_stars.jpg", "en": "Stars", "ru": "Звёзды", "aliases": ["звезды"]},
      {"file": "17_stork.jpg", "en": "Stork", "ru": "Аист", "aliases": []},
      {"file": "18_dog.jpg", "en": "Dog", "ru": "Собака", "aliases": ["пёс", "пес"]},
      {"file": "19_tower.jpg", "en": "Tower", "ru": "Башня", "aliases": []},
      {"file": "20_garden.jpg", "en": "Garden", "ru": "Сад", "aliases": ["парк"]},
      {"file": "21_mountain.jpg", "en": "Mountain", "ru": "Гора", "aliases": []},
      {"file": "22_crossroads.jpg", "en": "Crossroads", "ru": "Перекрёсток", "aliases": ["перекресток", "дороги"]},
      {"file": "23_mice.jpg", "en": "Mice", "ru": "Мыши", "aliases": ["крысы"]},
      {"file": "24_heart.jpg", "en": "Heart", "ru": "Сердце", "aliases": []},
      {"file": "25_ring.jpg", "en": "Ring", "ru": "Кольцо", "aliases": []},
      {"file": "26_book.jpg", "en": "Book", "ru": "Книга", "aliases": []},
      {"file": "27_letter.jpg", "en": "Letter", "ru": "Письмо", "aliases": []},
      {"file": "28_man.jpg", "en": "Man", "ru": "Мужчина", "aliases": ["господин"]},
      {"file": "29_woman.jpg", "en": "Woman", "ru": "Женщина", "aliases": ["госпожа", "дама"]},
      {"file": "30_lily.jpg", "en": "Lily", "ru": "Лилия", "aliases": []},
      {"file": "31_sun.jpg", "en": "Sun", "ru": "Солнце", "aliases": []},
      {"file": "32_moon.jpg", "en": "Moon", "ru": "Луна", "aliases": []},
      {"file": "33_key.jpg", "en": "Key", "ru": "Ключ", "aliases": []},
      {"file": "34_fish.jpg", "en": "Fish", "ru": "Рыбы", "aliases": ["рыба"]},
      {"file": "35_anchor.jpg", "en": "Anchor", "ru": "Якорь", "aliases": []},
      {"file": "36_cross.jpg", "en": "Cross", "ru": "Крест", "aliases": []}
    ]
  },
  "atlasnye": {
    "name_en": "Russian Playing Cards (Atlasnye)",
    "name_ru": "Атласные",
    "folder": "atlasnye",
    "status": "pending",
    "cards": [
      {"file": "06_hearts.jpg", "en": "Six of Hearts", "ru": "Шестёрка Червей", "aliases": ["6 червей"]},
      {"file": "07_hearts.jpg", "en": "Seven of Hearts", "ru": "Семёрка Червей", "aliases": ["7 червей"]},
      {"file": "08_hearts.jpg", "en": "Eight of Hearts", "ru": "Восьмёрка Червей", "aliases": ["8 червей"]},
      {"file": "09_hearts.jpg", "en": "Nine of Hearts", "ru": "Девятка Червей", "aliases": ["9 червей"]},
      {"file": "10_hearts.jpg", "en": "Ten of Hearts", "ru": "Десятка Червей", "aliases": ["10 червей"]},
      {"file": "jack_hearts.jpg", "en": "Jack of Hearts", "ru": "Валет Червей", "aliases": []},
      {"file": "queen_hearts.jpg", "en": "Queen of Hearts", "ru": "Дама Червей", "aliases": []},
      {"file": "king_hearts.jpg", "en": "King of Hearts", "ru": "Король Червей", "aliases": []},
      {"file": "ace_hearts.jpg", "en": "Ace of Hearts", "ru": "Туз Червей", "aliases": []},
      {"file": "06_diamonds.jpg", "en": "Six of Diamonds", "ru": "Шестёрка Бубен", "aliases": ["6 бубен"]},
      {"file": "07_diamonds.jpg", "en": "Seven of Diamonds", "ru": "Семёрка Бубен", "aliases": ["7 бубен"]},
      {"file": "08_diamonds.jpg", "en": "Eight of Diamonds", "ru": "Восьмёрка Бубен", "aliases": ["8 бубен"]},
      {"file": "09_diamonds.jpg", "en": "Nine of Diamonds", "ru": "Девятка Бубен", "aliases": ["9 бубен"]},
      {"file": "10_diamonds.jpg", "en": "Ten of Diamonds", "ru": "Десятка Бубен", "aliases": ["10 бубен"]},
      {"file": "jack_diamonds.jpg", "en": "Jack of Diamonds", "ru": "Валет Бубен", "aliases": []},
      {"file": "queen_diamonds.jpg", "en": "Queen of Diamonds", "ru": "Дама Бубен", "aliases": []},
      {"file": "king_diamonds.jpg", "en": "King of Diamonds", "ru": "Король Бубен", "aliases": []},
      {"file": "ace_diamonds.jpg", "en": "Ace of Diamonds", "ru": "Туз Бубен", "aliases": []},
      {"file": "06_clubs.jpg", "en": "Six of Clubs", "ru": "Шестёрка Треф", "aliases": ["6 треф"]},
      {"file": "07_clubs.jpg", "en": "Seven of Clubs", "ru": "Семёрка Треф", "aliases": ["7 треф"]},
      {"file": "08_clubs.jpg", "en": "Eight of Clubs", "ru": "Восьмёрка Треф", "aliases": ["8 треф"]},
      {"file": "09_clubs.jpg", "en": "Nine of Clubs", "ru": "Девятка Треф", "aliases": ["9 треф"]},
      {"file": "10_clubs.jpg", "en": "Ten of Clubs", "ru": "Десятка Треф", "aliases": ["10 треф"]},
      {"file": "jack_clubs.jpg", "en": "Jack of Clubs", "ru": "Валет Треф", "aliases": []},
      {"file": "queen_clubs.jpg", "en": "Queen of Clubs", "ru": "Дама Треф", "aliases": []},
      {"file": "king_clubs.jpg", "en": "King of Clubs", "ru": "Король Треф", "aliases": []},
      {"file": "ace_clubs.jpg", "en": "Ace of Clubs", "ru": "Туз Треф", "aliases": []},
      {"file": "06_spades.jpg", "en": "Six of Spades", "ru": "Шестёрка Пик", "aliases": ["6 пик"]},
      {"file": "07_spades.jpg", "en": "Seven of Spades", "ru": "Семёрка Пик", "aliases": ["7 пик"]},
      {"file": "08_spades.jpg", "en": "Eight of Spades", "ru": "Восьмёрка Пик", "aliases": ["8 пик"]},
      {"file": "09_spades.jpg", "en": "Nine of Spades", "ru": "Девятка Пик", "aliases": ["9 пик"]},
      {"file": "10_spades.jpg", "en": "Ten of Spades", "ru": "Десятка Пик", "aliases": ["10 пик"]},
      {"file": "jack_spades.jpg", "en": "Jack of Spades", "ru": "Валет Пик", "aliases": []},
      {"file": "queen_spades.jpg", "en": "Queen of Spades", "ru": "Дама Пик", "aliases": []},
      {"file": "king_spades.jpg", "en": "King of Spades", "ru": "Король Пик", "aliases": []},
      {"file": "ace_spades.jpg", "en": "Ace of Spades", "ru": "Туз Пик", "aliases": []}
    ]
  }
}
